{
  "$schema": "https://ui.shadcn.com/schema/registry-item.json",
  "name": "happy",
  "type": "registry:ui",
  "title": "Happy",
  "description": "Animated Happy icon from LivelyIcons",
  "dependencies": [
    "motion"
  ],
  "registryDependencies": [
    "lively-provider",
    "use-lively-animation",
    "lively-types"
  ],
  "files": [
    {
      "path": "icons/happy.tsx",
      "content": "\"use client\";\n\nimport * as React from \"react\";\nimport { motion } from \"motion/react\";\nimport { cn } from \"@/lib/utils\";\nimport { useLivelyAnimation } from \"@/hooks/use-lively-animation\";\nimport type { LivelyIconProps } from \"@/lib/lively-types\";\n\nconst Happy = React.forwardRef<SVGSVGElement, LivelyIconProps>(\n  (\n    {\n      size,\n      strokeWidth,\n      className,\n      animated,\n      lively = \"pulse\",\n      trigger = \"hover\",\n      \"aria-label\": ariaLabel,\n      ...props\n    },\n    ref\n  ) => {\n    const { animationProps, pathAnimationProps, drawWrapperProps } =\n      useLivelyAnimation(animated, lively, trigger);\n    const isDraw = lively === \"draw\";\n\n    const iconSize = size ?? \"var(--lively-icon-size, 24)\";\n    const iconStrokeWidth = strokeWidth ?? \"var(--lively-stroke-width, 2)\";\n\n    return (\n      <motion.svg\n        ref={ref}\n        width={iconSize}\n        height={iconSize}\n        viewBox=\"0 0 24 24\"\n        fill=\"none\"\n        stroke=\"currentColor\"\n        strokeWidth={iconStrokeWidth}\n        strokeLinecap=\"round\"\n        strokeLinejoin=\"round\"\n        className={cn(\"lively-icon\", isDraw && \"draw-animation\", className)}\n        {...(!isDraw ? animationProps : drawWrapperProps)}\n        role={ariaLabel ? \"img\" : undefined}\n        aria-label={ariaLabel}\n        aria-hidden={ariaLabel ? undefined : true}\n        {...props}\n      >\n        <motion.circle cx=\"12\" cy=\"12\" r=\"10\" {...(isDraw ? pathAnimationProps : {})} pathLength={1} className={isDraw ? 'draw-path' : ''}/>\n      <motion.path d=\"M8 14s1.5 2 4 2 4-2 4-2\" {...(isDraw ? pathAnimationProps : {})} pathLength={1} className={isDraw ? 'draw-path' : ''}/>\n      <motion.path d=\"M9 9h.01\" {...(isDraw ? pathAnimationProps : {})} pathLength={1} className={isDraw ? 'draw-path' : ''}/>\n      <motion.path d=\"M15 9h.01\" {...(isDraw ? pathAnimationProps : {})} pathLength={1} className={isDraw ? 'draw-path' : ''}/>\n      </motion.svg>\n    );\n  }\n);\n\nHappy.displayName = \"Happy\";\n\nexport { Happy };\n",
      "type": "registry:ui",
      "target": "components/icons/happy.tsx"
    }
  ]
}