{
  "$schema": "https://ui.shadcn.com/schema/registry-item.json",
  "name": "signal-app",
  "type": "registry:ui",
  "title": "SignalApp",
  "description": "Animated SignalApp icon from LivelyIcons",
  "dependencies": [
    "motion"
  ],
  "registryDependencies": [
    "lively-provider",
    "use-lively-animation",
    "lively-types"
  ],
  "files": [
    {
      "path": "icons/signal-app.tsx",
      "content": "\"use client\";\n\nimport * as React from \"react\";\nimport { motion } from \"motion/react\";\nimport { cn } from \"@/lib/utils\";\nimport { useLivelyAnimation } from \"@/hooks/use-lively-animation\";\nimport type { LivelyIconProps } from \"@/lib/lively-types\";\n\nconst SignalApp = React.forwardRef<SVGSVGElement, LivelyIconProps>(\n  (\n    {\n      size,\n      strokeWidth,\n      className,\n      animated,\n      lively = \"scale\",\n      trigger = \"hover\",\n      \"aria-label\": ariaLabel,\n      ...props\n    },\n    ref\n  ) => {\n    const { animationProps, pathAnimationProps, drawWrapperProps } =\n      useLivelyAnimation(animated, lively, trigger);\n    const isDraw = lively === \"draw\";\n\n    const iconSize = size ?? \"var(--lively-icon-size, 24)\";\n    const iconStrokeWidth = strokeWidth ?? \"var(--lively-stroke-width, 2)\";\n\n    return (\n      <motion.svg\n        ref={ref}\n        width={iconSize}\n        height={iconSize}\n        viewBox=\"0 0 24 24\"\n        fill=\"none\"\n        stroke=\"currentColor\"\n        strokeWidth={iconStrokeWidth}\n        strokeLinecap=\"round\"\n        strokeLinejoin=\"round\"\n        className={cn(\"lively-icon\", isDraw && \"draw-animation\", className)}\n        {...(!isDraw ? animationProps : drawWrapperProps)}\n        role={ariaLabel ? \"img\" : undefined}\n        aria-label={ariaLabel}\n        aria-hidden={ariaLabel ? undefined : true}\n        {...props}\n      >\n        {/* Speech bubble */}\n      <motion.path d=\"M21 11.5a8.38 8.38 0 0 1-.9 3.8 8.5 8.5 0 0 1-7.6 4.7 8.38 8.38 0 0 1-3.8-.9L3 21l1.9-5.7a8.38 8.38 0 0 1-.9-3.8 8.5 8.5 0 0 1 4.7-7.6 8.38 8.38 0 0 1 3.8-.9h.5a8.48 8.48 0 0 1 8 8v.5z\" {...(isDraw ? pathAnimationProps : {})} pathLength={1} className={isDraw ? 'draw-path' : ''}/>\n      {/* Signal dot */}\n      <motion.circle cx=\"12\" cy=\"11\" r=\"2\" {...(isDraw ? pathAnimationProps : {})} pathLength={1} className={isDraw ? 'draw-path' : ''}/>\n      </motion.svg>\n    );\n  }\n);\n\nSignalApp.displayName = \"SignalApp\";\n\nexport { SignalApp };\n",
      "type": "registry:ui",
      "target": "components/icons/signal-app.tsx"
    }
  ]
}